pypewriter_cli/Pypewriter.py
pypewriter_cli/__about__.py
pypewriter_cli/__init__.py
pypewriter_cli-0.0.1.dist-info/METADATA
pypewriter_cli-0.0.1.dist-info/WHEEL
pypewriter_cli-0.0.1.dist-info/licenses/LICENSE.txt
pypewriter_cli-0.0.1.dist-info/RECORD
